CHANGES.txt
LICENSE.txt
MANIFEST.in
README.txt
requirements.txt
setup.py
proxyenv/__init__.py
proxyenv/proxyenv.py
proxyenv.egg-info/PKG-INFO
proxyenv.egg-info/SOURCES.txt
proxyenv.egg-info/dependency_links.txt
proxyenv.egg-info/entry_points.txt
proxyenv.egg-info/requires.txt
proxyenv.egg-info/top_level.txt