Metadata-Version: 1.1
Name: proxyenv
Version: 0.5.1
Summary: Create HTTP proxy environment using docker
Home-page: http://pypi.python.org/pypi/proxyenv/
Author: Martin Wilck
Author-email: mwilck@arcor.de
License: LICENSE.txt
Keywords: squid,testing,http,proxy,docker
Platform: UNKNOWN
Classifier: Development Status :: 3 - Alpha
Classifier: Intended Audience :: Developers
Classifier: License :: OSI Approved :: MIT License
Classifier: Environment :: Console
Classifier: Natural Language :: English
Classifier: Operating System :: POSIX :: Linux
Classifier: Programming Language :: Python :: 2
Classifier: Programming Language :: Python :: 3
Classifier: Topic :: Software Development :: Testing
Classifier: Topic :: Internet :: Proxy Servers
